{"name":"Select Toruń","id":"go-to-checkout-using-pickup-delivery;select-toruń","testSteps":[{"number":1,"description":"Given that Ellen happens to be on the checkout with a product on testServerDajar","duration":27216,"startTime":"2022-03-31T14:00:03.751044+02:00[Europe/Warsaw]","screenshots":[{"screenshot":"d1aabb432c1aae2052a1c6f4356bd268cb17afa01e9862fcee426ddb8354c1ba.png","timeStamp":1648728030967}],"result":"SUCCESS","precondition":false,"level":0,"children":[{"number":2,"description":"Ellen prepares site","duration":9004,"startTime":"2022-03-31T14:00:03.756247+02:00[Europe/Warsaw]","screenshots":[{"screenshot":"88206c75903d7d0190db15a55b893281bd3ec8e89dc685568fb4140881c28849.png","timeStamp":1648728012761}],"result":"SUCCESS","precondition":false,"level":1,"children":[{"number":3,"description":"Ellen opens the application","duration":7087,"startTime":"2022-03-31T14:00:03.758131+02:00[Europe/Warsaw]","screenshots":[{"screenshot":"43b3cd8ebcbbb3f24cb693e77d893026dfdde61d71d1800da1fe8ea2fb326a11.png","timeStamp":1648728010845}],"result":"SUCCESS","precondition":false,"level":2,"children":[{"number":4,"description":"Ellen opens the home.page.test.dajar page","duration":7082,"startTime":"2022-03-31T14:00:03.759708+02:00[Europe/Warsaw]","screenshots":[{"screenshot":"43b3cd8ebcbbb3f24cb693e77d893026dfdde61d71d1800da1fe8ea2fb326a11.png","timeStamp":1648728010842}],"result":"SUCCESS","precondition":false,"level":3}]},{"number":5,"description":"Ellen accepts cookies","duration":1913,"startTime":"2022-03-31T14:00:10.845821+02:00[Europe/Warsaw]","screenshots":[{"screenshot":"43b3cd8ebcbbb3f24cb693e77d893026dfdde61d71d1800da1fe8ea2fb326a11.png","timeStamp":1648728010848},{"screenshot":"88206c75903d7d0190db15a55b893281bd3ec8e89dc685568fb4140881c28849.png","timeStamp":1648728012759}],"result":"SUCCESS","precondition":false,"level":2,"children":[{"number":6,"description":"Ellen clicks on Accept Cookies Button","duration":1906,"startTime":"2022-03-31T14:00:10.849759+02:00[Europe/Warsaw]","screenshots":[{"screenshot":"43b3cd8ebcbbb3f24cb693e77d893026dfdde61d71d1800da1fe8ea2fb326a11.png","timeStamp":1648728010853},{"screenshot":"88206c75903d7d0190db15a55b893281bd3ec8e89dc685568fb4140881c28849.png","timeStamp":1648728012756}],"result":"SUCCESS","precondition":false,"level":3}]}]},{"number":7,"description":"Ellen clicks #category","duration":4822,"startTime":"2022-03-31T14:00:12.761660+02:00[Europe/Warsaw]","screenshots":[{"screenshot":"88206c75903d7d0190db15a55b893281bd3ec8e89dc685568fb4140881c28849.png","timeStamp":1648728012763},{"screenshot":"731a422deaecd836410db2d811c4552a9b970fd017e861ffdddc85c2d7379eea.png","timeStamp":1648728017584}],"result":"SUCCESS","precondition":false,"level":1,"children":[{"number":8,"description":"Ellen clicks on [[ChromeDriver: chrome on LINUX (3614b450878db9e6cf587f974ed6a704)] -\u003e xpath: (//div[@data-test\u003d\u0027main-categories\u0027])[2]/button]","duration":1410,"startTime":"2022-03-31T14:00:12.851322+02:00[Europe/Warsaw]","screenshots":[{"screenshot":"88206c75903d7d0190db15a55b893281bd3ec8e89dc685568fb4140881c28849.png","timeStamp":1648728013831},{"screenshot":"f7e580ea3f2b3cb1706c85ffb8e09a133bc085548b37fd54d71e67e692294d24.png","timeStamp":1648728014261}],"result":"SUCCESS","precondition":false,"level":2}]},{"number":9,"description":"Ellen opens page of a product","duration":4038,"startTime":"2022-03-31T14:00:17.584558+02:00[Europe/Warsaw]","screenshots":[{"screenshot":"731a422deaecd836410db2d811c4552a9b970fd017e861ffdddc85c2d7379eea.png","timeStamp":1648728017586},{"screenshot":"47b0accc5014c960181369acdfc01ea8b174bd170f4bafa8174390eced3ea60d.png","timeStamp":1648728021622}],"result":"SUCCESS","precondition":false,"level":1,"children":[{"number":10,"description":"Ellen clicks on [[ChromeDriver: chrome on LINUX (3614b450878db9e6cf587f974ed6a704)] -\u003e xpath: //div[@data-test\u003d\u0027product-box\u0027]/a/div/p]","duration":733,"startTime":"2022-03-31T14:00:17.647327+02:00[Europe/Warsaw]","screenshots":[{"screenshot":"9417c25400e1862a2dfb6d231668775739576979c44baf4b834c179223b5c592.png","timeStamp":1648728018013},{"screenshot":"f743c44002f96f5372c5aa8aa1eabcb5c2a69e3b6da9e57ac218ea5450cdf72a.png","timeStamp":1648728018380}],"result":"SUCCESS","precondition":false,"level":2}]},{"number":11,"description":"Ellen adds product to cart","duration":5130,"startTime":"2022-03-31T14:00:21.623441+02:00[Europe/Warsaw]","screenshots":[{"screenshot":"47b0accc5014c960181369acdfc01ea8b174bd170f4bafa8174390eced3ea60d.png","timeStamp":1648728021625},{"screenshot":"fd2433eba088ac417ef2b86c0b59bff3f62d5a01828c4ac9d113a1875f775adb.png","timeStamp":1648728026753}],"result":"SUCCESS","precondition":false,"level":1,"children":[{"number":12,"description":"Ellen clicks on Add to cart button","duration":704,"startTime":"2022-03-31T14:00:21.668162+02:00[Europe/Warsaw]","screenshots":[{"screenshot":"47b0accc5014c960181369acdfc01ea8b174bd170f4bafa8174390eced3ea60d.png","timeStamp":1648728021670},{"screenshot":"1607a8fa0e8374775453529945ae6635fa8f0941038fc506de3b9244918dfb87.png","timeStamp":1648728022372}],"result":"SUCCESS","precondition":false,"level":2}]},{"number":13,"description":"Ellen moves the mouse down","duration":652,"startTime":"2022-03-31T14:00:26.754356+02:00[Europe/Warsaw]","screenshots":[{"screenshot":"fd2433eba088ac417ef2b86c0b59bff3f62d5a01828c4ac9d113a1875f775adb.png","timeStamp":1648728026756},{"screenshot":"fd2433eba088ac417ef2b86c0b59bff3f62d5a01828c4ac9d113a1875f775adb.png","timeStamp":1648728027406}],"result":"SUCCESS","precondition":false,"level":1},{"number":14,"description":"Ellen opens mini cart","duration":800,"startTime":"2022-03-31T14:00:27.407881+02:00[Europe/Warsaw]","screenshots":[{"screenshot":"fd2433eba088ac417ef2b86c0b59bff3f62d5a01828c4ac9d113a1875f775adb.png","timeStamp":1648728027409},{"screenshot":"ede579f3a6482c461b144e1e9e8ba932bf904bec69690b50689032f98be65623.png","timeStamp":1648728028208}],"result":"SUCCESS","precondition":false,"level":1,"children":[{"number":15,"description":"Ellen clicks on Mini cart button","duration":767,"startTime":"2022-03-31T14:00:27.438138+02:00[Europe/Warsaw]","screenshots":[{"screenshot":"fd2433eba088ac417ef2b86c0b59bff3f62d5a01828c4ac9d113a1875f775adb.png","timeStamp":1648728027440},{"screenshot":"ede579f3a6482c461b144e1e9e8ba932bf904bec69690b50689032f98be65623.png","timeStamp":1648728028206}],"result":"SUCCESS","precondition":false,"level":2}]},{"number":16,"description":"Ellen opens checkout page","duration":2756,"startTime":"2022-03-31T14:00:28.209039+02:00[Europe/Warsaw]","screenshots":[{"screenshot":"ede579f3a6482c461b144e1e9e8ba932bf904bec69690b50689032f98be65623.png","timeStamp":1648728028210},{"screenshot":"d1aabb432c1aae2052a1c6f4356bd268cb17afa01e9862fcee426ddb8354c1ba.png","timeStamp":1648728030965}],"result":"SUCCESS","precondition":false,"level":1,"children":[{"number":17,"description":"Ellen clicks on Go to checkout button","duration":489,"startTime":"2022-03-31T14:00:28.234506+02:00[Europe/Warsaw]","screenshots":[{"screenshot":"ede579f3a6482c461b144e1e9e8ba932bf904bec69690b50689032f98be65623.png","timeStamp":1648728028236},{"screenshot":"4e79618ca200d7d4fc1efb403a6373ad950a69224a7c734902091c8d3f0bc551.png","timeStamp":1648728028723}],"result":"SUCCESS","precondition":false,"level":2}]}]},{"number":18,"description":"When she selects delivery type pickup and chooses Toruń as a person","duration":1,"startTime":"2022-03-31T14:00:30.967342+02:00[Europe/Warsaw]","screenshots":[{"screenshot":"d1aabb432c1aae2052a1c6f4356bd268cb17afa01e9862fcee426ddb8354c1ba.png","timeStamp":1648728030968}],"result":"PENDING","precondition":false,"level":0},{"number":19,"description":"Then he should make the order as a person using transfer","duration":1,"startTime":"2022-03-31T14:00:30.969658+02:00[Europe/Warsaw]","result":"IGNORED","precondition":false,"level":0}],"userStory":{"id":"go-to-checkout-using-pickup-delivery","storyName":"Go to checkout using pickup delivery","path":"checkout/test/dajar/go_to_checkout_using_pickup_delivery.feature","narrative":"  Customer should be able to make orders by using pick up delivery","type":"feature"},"featureTag":{"name":"Dajar/Go to checkout using pickup delivery","type":"feature","displayName":"Dajar/Go to checkout using pickup delivery"},"title":"Select Toruń","description":"","tags":[{"name":"Dajar/Go to checkout using pickup delivery","type":"feature","displayName":"Go to checkout using pickup delivery"},{"name":"Checkout/Production","type":"theme","displayName":"Production"},{"name":"Checkout","type":"theme","displayName":"Checkout"},{"name":"Production/Pl","type":"capability","displayName":"Pl"},{"name":"Checkout/Test","type":"theme","displayName":"Test"},{"name":"Test/Dajar","type":"capability","displayName":"Dajar"},{"name":"Pl/Go to checkout using pickup delivery","type":"feature","displayName":"Go to checkout using pickup delivery"}],"startTime":"2022-03-31T14:00:03.749054+02:00[Europe/Warsaw]","duration":27222,"projectKey":"","annotatedResult":"PENDING","sessionId":"3614b450878db9e6cf587f974ed6a704","driver":"chrome:ellen","isManualTestingUpToDate":false,"manual":false,"testSource":"Cucumber","actors":[{"name":"Ellen","can":["com.deosite.tests.abilities.Load@7d28d525","browse the web"]}],"result":"PENDING"}